AUTHORS
LICENSE
MANIFEST.in
README.rst
setup.py
djcommon/__init__.py
djcommon/admin.py
djcommon/admin_forms.py
djcommon/auth.py
djcommon/context_processors.py
djcommon/csv.py
djcommon/decorators.py
djcommon/email.py
djcommon/fields.py
djcommon/forms.py
djcommon/helpers.py
djcommon/http.py
djcommon/middleware.py
djcommon/models.py
djcommon/pdf.py
djcommon/routers.py
djcommon/template.py
djcommon/views.py
djcommon/xml.py
djcommon.egg-info/PKG-INFO
djcommon.egg-info/SOURCES.txt
djcommon.egg-info/dependency_links.txt
djcommon.egg-info/not-zip-safe
djcommon.egg-info/top_level.txt
djcommon/apps/__init__.py
djcommon/apps/translations/__init__.py
djcommon/apps/translations/models.py
djcommon/apps/translations/migrations/0001_initial.py
djcommon/apps/translations/migrations/__init__.py
djcommon/conf/__init__.py
djcommon/conf/countries.py
djcommon/locale/en/LC_MESSAGES/django.mo
djcommon/locale/en/LC_MESSAGES/django.po
djcommon/static/js/collapsed_stacked_inlines.js
djcommon/static/js/collapsed_tabular_inlines.js
djcommon/static/js/ordering_inlines.js
djcommon/templates/admin/add_without_inlines.html
djcommon/templatetags/__init__.py
djcommon/templatetags/common.py
djcommon/templatetags/development.py
djcommon/tests/__init__.py
djcommon/tests/fields.py
djcommon/tests/runners.py
djcommon/widgets/__init__.py
djcommon/widgets/admin.py