Metadata-Version: 1.1
Name: djcommon
Version: 1.1.0
Summary: Django Common (djcommon) - A set of project independent reusable features while developing with the Django Framework - https://www.djangoproject.com/ 
Home-page: http://github.com/baskoopmans/djcommon/
Author: Bas Koopmans
Author-email: django@baskoopmans.nl
License: BSD
Download-URL: http://github.com/baskoopmans/djcommon/downloads
Platform: UNKNOWN
Classifier: Development Status :: 4 - Beta
Classifier: Environment :: Web Environment
Classifier: Framework :: Django
Classifier: Intended Audience :: Developers
Classifier: License :: OSI Approved :: BSD License
Classifier: Operating System :: OS Independent
Classifier: Programming Language :: Python
Classifier: Topic :: Software Development :: Libraries :: Python Modules
